<?xml version="1.0" encoding="utf-8"?>
<SdkMessageProcessingStep Name="BDP.DPAM.Plugins.OpportunityClose.PreCreateOpportunityClose: Create of opportunityclose" SdkMessageProcessingStepId="{7738cddb-e092-ec11-b400-6045bd878fef}" xmlns:xsi="http://www.w3.org/2001/XMLSchema-instance">
  <SdkMessageId>9ebdbb1b-ea3e-db11-86a7-000a3a5473e8</SdkMessageId>
  <PluginTypeName>BDP.DPAM.Plugins.OpportunityClose.PreCreateOpportunityClose, BDP.DPAM.Plugins.OpportunityClose, Version=1.0.0.0, Culture=neutral, PublicKeyToken=80b185f96446b420</PluginTypeName>
  <PluginTypeId>a0ad15a5-54d8-4947-9645-82af4a020579</PluginTypeId>
  <PrimaryEntity>opportunityclose</PrimaryEntity>
  <AsyncAutoDelete>0</AsyncAutoDelete>
  <FilteringAttributes></FilteringAttributes>
  <InvocationSource>1</InvocationSource>
  <Mode>0</Mode>
  <Rank>1</Rank>
  <EventHandlerTypeCode>4602</EventHandlerTypeCode>
  <Stage>20</Stage>
  <IsCustomizable>1</IsCustomizable>
  <IsHidden>0</IsHidden>
  <SupportedDeployment>0</SupportedDeployment>
  <IntroducedVersion>1.0</IntroducedVersion>
  <SdkMessageProcessingStepImages />
</SdkMessageProcessingStep>